{
    "pages": [
        {
            "page": 1,
            "md": "# Table of Contents\n\n- **ISO AUTO SETTING** .......................................................... 149\n- **CONVERSION LENS** ......................................................... 150\n- **DIGITAL TELE-CONV.** ...................................................... 150\n- **ND FILTER** ........................................................................... 150\n- **WIRELESS COMMUNICATION** ....................................... 151\n\n## FLASH SETTING ................................................................. 152\n- **FLASH FUNCTION SETTING** ........................................... 152\n- **RED EYE REMOVAL** .......................................................... 152\n- **TTL-LOCK MODE** .............................................................. 153\n- **LED LIGHT SETTING** ......................................................... 153\n- **MASTER SETTING** ............................................................. 154\n- **CH SETTING** ....................................................................... 154\n- **Built-In Flash** ...................................................................... 154\n\n## MOVIE SETTING ................................................................. 155\n- **MOVIE MODE** ..................................................................... 155\n- **FULL HD HIGH SPEED REC** ............................................. 156\n- **🎥 FILM SIMULATION** ......................................................... 157\n- **🎥 MONOCHROMATIC COLOR** ......................................... 157\n- **🎥 DYNAMIC RANGE** .......................................................... 158\n- **🎥 WHITE BALANCE** .......................................................... 158\n- **🎥 TONE CURVE** .................................................................. 159\n- **🎥 COLOR** ............................................................................. 159\n- **🎥 SHARPNESS** ................................................................... 159\n- **🎥 NOISE REDUCTION** ....................................................... 160\n- **4K INTERFRAME NR** ......................................................... 160\n- **F-Log RECORDING** ........................................................... 161\n- **🎥 PERIPHERAL LIGHT CORRECTION** ............................ 161\n- **🎥 FOCUS AREA** .................................................................. 161\n- **MOVIE AF MODE** ............................................................... 162\n- **🎥 AF-C CUSTOM SETTING** ............................................... 162\n- **🎥 FACE/EYE DETECTION SETTING** ............................... 163\n- **🎥 MF ASSIST** ....................................................................... 163\n- **🎥 FOCUS CHECK** ............................................................... 164\n- **HDMI OUTPUT INFO DISPLAY** ........................................ 164\n- **4K MOVIE OUTPUT** ........................................................... 165\n- **FULL HD MOVIE OUTPUT** ................................................ 165\n- **4K HDMI STANDBY QUALITY** ......................................... 166\n- **HDMI REC CONTROL** ....................................................... 166",
            "images": [
                {
                    "name": "page_1.jpg",
                    "height": 0,
                    "width": 0,
                    "x": 0,
                    "y": 0,
                    "type": "full_page_screenshot"
                }
            ],
            "charts": [],
            "items": [
                {
                    "type": "heading",
                    "lvl": 1,
                    "value": "Table of Contents",
                    "md": "# Table of Contents"
                },
                {
                    "type": "text",
                    "value": "- **ISO AUTO SETTING** .......................................................... 149\n- **CONVERSION LENS** ......................................................... 150\n- **DIGITAL TELE-CONV.** ...................................................... 150\n- **ND FILTER** ........................................................................... 150\n- **WIRELESS COMMUNICATION** ....................................... 151",
                    "md": "- **ISO AUTO SETTING** .......................................................... 149\n- **CONVERSION LENS** ......................................................... 150\n- **DIGITAL TELE-CONV.** ...................................................... 150\n- **ND FILTER** ........................................................................... 150\n- **WIRELESS COMMUNICATION** ....................................... 151"
                },
                {
                    "type": "heading",
                    "lvl": 2,
                    "value": "FLASH SETTING ................................................................. 152",
                    "md": "## FLASH SETTING ................................................................. 152"
                },
                {
                    "type": "text",
                    "value": "- **FLASH FUNCTION SETTING** ........................................... 152\n- **RED EYE REMOVAL** .......................................................... 152\n- **TTL-LOCK MODE** .............................................................. 153\n- **LED LIGHT SETTING** ......................................................... 153\n- **MASTER SETTING** ............................................................. 154\n- **CH SETTING** ....................................................................... 154\n- **Built-In Flash** ...................................................................... 154",
                    "md": "- **FLASH FUNCTION SETTING** ........................................... 152\n- **RED EYE REMOVAL** .......................................................... 152\n- **TTL-LOCK MODE** .............................................................. 153\n- **LED LIGHT SETTING** ......................................................... 153\n- **MASTER SETTING** ............................................................. 154\n- **CH SETTING** ....................................................................... 154\n- **Built-In Flash** ...................................................................... 154"
                },
                {
                    "type": "heading",
                    "lvl": 2,
                    "value": "MOVIE SETTING ................................................................. 155",
                    "md": "## MOVIE SETTING ................................................................. 155"
                },
                {
                    "type": "text",
                    "value": "- **MOVIE MODE** ..................................................................... 155\n- **FULL HD HIGH SPEED REC** ............................................. 156\n- **🎥 FILM SIMULATION** ......................................................... 157\n- **🎥 MONOCHROMATIC COLOR** ......................................... 157\n- **🎥 DYNAMIC RANGE** .......................................................... 158\n- **🎥 WHITE BALANCE** .......................................................... 158\n- **🎥 TONE CURVE** .................................................................. 159\n- **🎥 COLOR** ............................................................................. 159\n- **🎥 SHARPNESS** ................................................................... 159\n- **🎥 NOISE REDUCTION** ....................................................... 160\n- **4K INTERFRAME NR** ......................................................... 160\n- **F-Log RECORDING** ........................................................... 161\n- **🎥 PERIPHERAL LIGHT CORRECTION** ............................ 161\n- **🎥 FOCUS AREA** .................................................................. 161\n- **MOVIE AF MODE** ............................................................... 162\n- **🎥 AF-C CUSTOM SETTING** ............................................... 162\n- **🎥 FACE/EYE DETECTION SETTING** ............................... 163\n- **🎥 MF ASSIST** ....................................................................... 163\n- **🎥 FOCUS CHECK** ............................................................... 164\n- **HDMI OUTPUT INFO DISPLAY** ........................................ 164\n- **4K MOVIE OUTPUT** ........................................................... 165\n- **FULL HD MOVIE OUTPUT** ................................................ 165\n- **4K HDMI STANDBY QUALITY** ......................................... 166\n- **HDMI REC CONTROL** ....................................................... 166",
                    "md": "- **MOVIE MODE** ..................................................................... 155\n- **FULL HD HIGH SPEED REC** ............................................. 156\n- **🎥 FILM SIMULATION** ......................................................... 157\n- **🎥 MONOCHROMATIC COLOR** ......................................... 157\n- **🎥 DYNAMIC RANGE** .......................................................... 158\n- **🎥 WHITE BALANCE** .......................................................... 158\n- **🎥 TONE CURVE** .................................................................. 159\n- **🎥 COLOR** ............................................................................. 159\n- **🎥 SHARPNESS** ................................................................... 159\n- **🎥 NOISE REDUCTION** ....................................................... 160\n- **4K INTERFRAME NR** ......................................................... 160\n- **F-Log RECORDING** ........................................................... 161\n- **🎥 PERIPHERAL LIGHT CORRECTION** ............................ 161\n- **🎥 FOCUS AREA** .................................................................. 161\n- **MOVIE AF MODE** ............................................................... 162\n- **🎥 AF-C CUSTOM SETTING** ............................................... 162\n- **🎥 FACE/EYE DETECTION SETTING** ............................... 163\n- **🎥 MF ASSIST** ....................................................................... 163\n- **🎥 FOCUS CHECK** ............................................................... 164\n- **HDMI OUTPUT INFO DISPLAY** ........................................ 164\n- **4K MOVIE OUTPUT** ........................................................... 165\n- **FULL HD MOVIE OUTPUT** ................................................ 165\n- **4K HDMI STANDBY QUALITY** ......................................... 166\n- **HDMI REC CONTROL** ....................................................... 166"
                }
            ],
            "status": "OK",
            "links": [],
            "triggeredAutoMode": false,
            "structuredData": null,
            "noStructuredContent": false,
            "noTextContent": false
        }
    ],
    "job_metadata": {
        "credits_used": 534.0,
        "job_credits_usage": 10,
        "job_pages": 1,
        "job_auto_mode_triggered_pages": 0,
        "job_is_cache_hit": false,
        "credits_max": 1000
    },
    "job_id": "2a78abe7-3265-40e0-9e0f-674fed87f93c",
    "file_path": "../data/raw_data/x100v/x100v_split/x100v_page13.pdf"
}