{
    "pages": [
        {
            "page": 1,
            "md": "# Focus Check\n\nIf **ON** is selected, the display will automatically zoom in on the selected focus area when the focus ring is rotated in manual focus mode.\n\n| Options |     |\n|---------|-----|\n| ON      | OFF |\n\n# HDMI Output Info Display\n\nIf **ON** is selected, HDMI devices to which the camera is connected will mirror the information in the camera display.\n\n| Options |     |\n|---------|-----|\n| ON      | OFF |",
            "images": [
                {
                    "name": "page_1.jpg",
                    "height": 0,
                    "width": 0,
                    "x": 0,
                    "y": 0,
                    "type": "full_page_screenshot"
                }
            ],
            "charts": [],
            "items": [
                {
                    "type": "heading",
                    "lvl": 1,
                    "value": "Focus Check",
                    "md": "# Focus Check"
                },
                {
                    "type": "text",
                    "value": "If **ON** is selected, the display will automatically zoom in on the selected focus area when the focus ring is rotated in manual focus mode.",
                    "md": "If **ON** is selected, the display will automatically zoom in on the selected focus area when the focus ring is rotated in manual focus mode."
                },
                {
                    "type": "table",
                    "rows": [
                        [
                            "Options",
                            ""
                        ],
                        [
                            "ON",
                            "OFF"
                        ]
                    ],
                    "md": "| Options |     |\n|---------|-----|\n| ON      | OFF |",
                    "isPerfectTable": true,
                    "csv": "\"Options\",\"\"\n\"ON\",\"OFF\""
                },
                {
                    "type": "heading",
                    "lvl": 1,
                    "value": "HDMI Output Info Display",
                    "md": "# HDMI Output Info Display"
                },
                {
                    "type": "text",
                    "value": "If **ON** is selected, HDMI devices to which the camera is connected will mirror the information in the camera display.",
                    "md": "If **ON** is selected, HDMI devices to which the camera is connected will mirror the information in the camera display."
                },
                {
                    "type": "table",
                    "rows": [
                        [
                            "Options",
                            ""
                        ],
                        [
                            "ON",
                            "OFF"
                        ]
                    ],
                    "md": "| Options |     |\n|---------|-----|\n| ON      | OFF |",
                    "isPerfectTable": true,
                    "csv": "\"Options\",\"\"\n\"ON\",\"OFF\""
                }
            ],
            "status": "OK",
            "links": [],
            "triggeredAutoMode": false,
            "structuredData": null,
            "noStructuredContent": false,
            "noTextContent": false
        }
    ],
    "job_metadata": {
        "credits_used": 644.0,
        "job_credits_usage": 10,
        "job_pages": 1,
        "job_auto_mode_triggered_pages": 0,
        "job_is_cache_hit": false,
        "credits_max": 1000
    },
    "job_id": "5b466808-83e1-41f9-b577-ea6fa6a3a759",
    "file_path": "../data/raw_data/x100v/x100v_split/x100v_page184.pdf"
}