{
    "api": "2.0",
    "content": {
        "html": "<header id='0' style='font-size:16px'>Parts of the Camera</header>\n<p id='1' data-category='paragraph' style='font-size:18px'>1</p>\n<br><figure id='2'><img style='font-size:14px' alt=\"express\nCF\nOS\n50 46\" data-coord=\"top-left:(405,584); bottom-right:(2368,1652)\" /></figure>\n<p id='3' data-category='paragraph' style='font-size:14px'>32 DRIVE button 8</p>\n<br><p id='4' data-category='list' style='font-size:18px'>33 面 (delete) button 66<br>34 Focus mode selector 93<br>35 AFON button 111, 385<br>36 Rear command dial 9, 218, 358<br>37 Q (quick menu) button 379<br>38 Indicator lamp 10, 192<br>Tally light. 192<br>39 Headphonejack cover<br>40 Memory card slot cover latch. 45<br>41 Memory card slot cover (detachable)</p>\n<br><p id='5' data-category='paragraph' style='font-size:18px'>6, 45</p>\n<br><p id='6' data-category='list' style='font-size:18px'>42 Battery-chamber cover latch 43<br>43 Hole to hook Vertical Battery Grip<br>44 Battery-chamber cover. 43<br>45 DISP (display)/ BACK button 22, 216</p>\n<br><p id='7' data-category='list' style='font-size:18px'>46 (playback) button 63<br>47 Speaker 73, 341<br>48 MENU/OK button 32<br>49 AEL (exposure lock) button 111, 385<br>50 Focus stick (focus lever). 6, 98, 357<br>51 Tripod mount<br>52 Vertical battery grip connector cover · 411<br>53 Tilt lock release 11<br>54 LCD monitor 11, 18, 20<br>Touch screen 34, 162, 203<br>55 Headphonejack (⌀3.5mm) 207<br>56 Memory card slot 1<br>(for Type B CFexpress cards) 45<br>57 Memory card slot 2<br>(for SD memory cards) 45</p>\n<footer id='8' style='font-size:20px'>3</footer>\n<br><footer id='9' style='font-size:22px'>Before<br>You<br>Begin</footer>",
        "markdown": "Parts of the Camera\n\n1\n\n![image](/image/placeholder)\nexpress\nCF\nOS\n50 46\n\n32 DRIVE button 8\n\n- 33 面 (delete) button 66\n- 34 Focus mode selector 93\n- 35 AFON button 111, 385\n- 36 Rear command dial 9, 218, 358\n- 37 Q (quick menu) button 379\n- 38 Indicator lamp 10, 192\n- Tally light. 192\n- 39 Headphonejack cover\n- 40 Memory card slot cover latch. 45\n- 41 Memory card slot cover (detachable)\n\n\n6, 45\n\n- 42 Battery-chamber cover latch 43\n- 43 Hole to hook Vertical Battery Grip\n- 44 Battery-chamber cover. 43\n- 45 DISP (display)/ BACK button 22, 216\n\n\n- 46 (playback) button 63\n- 47 Speaker 73, 341\n- 48 MENU/OK button 32\n- 49 AEL (exposure lock) button 111, 385\n- 50 Focus stick (focus lever). 6, 98, 357\n- 51 Tripod mount\n- 52 Vertical battery grip connector cover · 411\n- 53 Tilt lock release 11\n- 54 LCD monitor 11, 18, 20\n- Touch screen 34, 162, 203\n- 55 Headphonejack (⌀3.5mm) 207\n- 56 Memory card slot 1\n- (for Type B CFexpress cards) 45\n- 57 Memory card slot 2\n- (for SD memory cards) 45\n\n\n3\n\nBefore\nYou\nBegin",
        "text": ""
    },
    "elements": [
        {
            "category": "header",
            "content": {
                "html": "<header id='0' style='font-size:16px'>Parts of the Camera</header>",
                "markdown": "Parts of the Camera",
                "text": ""
            },
            "coordinates": [
                {
                    "x": 0.7226,
                    "y": 0.0295
                },
                {
                    "x": 0.9186,
                    "y": 0.0295
                },
                {
                    "x": 0.9186,
                    "y": 0.0492
                },
                {
                    "x": 0.7226,
                    "y": 0.0492
                }
            ],
            "id": 0,
            "page": 1
        },
        {
            "category": "paragraph",
            "content": {
                "html": "<p id='1' data-category='paragraph' style='font-size:18px'>1</p>",
                "markdown": "1",
                "text": ""
            },
            "coordinates": [
                {
                    "x": 0.9601,
                    "y": 0.2403
                },
                {
                    "x": 0.972,
                    "y": 0.2403
                },
                {
                    "x": 0.972,
                    "y": 0.2558
                },
                {
                    "x": 0.9601,
                    "y": 0.2558
                }
            ],
            "id": 1,
            "page": 1
        },
        {
            "category": "figure",
            "content": {
                "html": "<br><figure id='2'><img style='font-size:14px' alt=\"express\nCF\nOS\n50 46\" data-coord=\"top-left:(405,584); bottom-right:(2368,1652)\" /></figure>",
                "markdown": "![image](/image/placeholder)\nexpress\nCF\nOS\n50 46",
                "text": ""
            },
            "coordinates": [
                {
                    "x": 0.1468,
                    "y": 0.1498
                },
                {
                    "x": 0.857,
                    "y": 0.1498
                },
                {
                    "x": 0.857,
                    "y": 0.424
                },
                {
                    "x": 0.1468,
                    "y": 0.424
                }
            ],
            "id": 2,
            "page": 1
        },
        {
            "category": "paragraph",
            "content": {
                "html": "<p id='3' data-category='paragraph' style='font-size:14px'>32 DRIVE button 8</p>",
                "markdown": "32 DRIVE button 8",
                "text": ""
            },
            "coordinates": [
                {
                    "x": 0.111,
                    "y": 0.4807
                },
                {
                    "x": 0.5051,
                    "y": 0.4807
                },
                {
                    "x": 0.5051,
                    "y": 0.4999
                },
                {
                    "x": 0.111,
                    "y": 0.4999
                }
            ],
            "id": 3,
            "page": 1
        },
        {
            "category": "list",
            "content": {
                "html": "<br><p id='4' data-category='list' style='font-size:18px'>33 面 (delete) button 66<br>34 Focus mode selector 93<br>35 AFON button 111, 385<br>36 Rear command dial 9, 218, 358<br>37 Q (quick menu) button 379<br>38 Indicator lamp 10, 192<br>Tally light. 192<br>39 Headphonejack cover<br>40 Memory card slot cover latch. 45<br>41 Memory card slot cover (detachable)</p>",
                "markdown": "- 33 面 (delete) button 66\n- 34 Focus mode selector 93\n- 35 AFON button 111, 385\n- 36 Rear command dial 9, 218, 358\n- 37 Q (quick menu) button 379\n- 38 Indicator lamp 10, 192\n- Tally light. 192\n- 39 Headphonejack cover\n- 40 Memory card slot cover latch. 45\n- 41 Memory card slot cover (detachable)\n",
                "text": ""
            },
            "coordinates": [
                {
                    "x": 0.1178,
                    "y": 0.4924
                },
                {
                    "x": 0.5085,
                    "y": 0.4924
                },
                {
                    "x": 0.5085,
                    "y": 0.705
                },
                {
                    "x": 0.1178,
                    "y": 0.705
                }
            ],
            "id": 4,
            "page": 1
        },
        {
            "category": "paragraph",
            "content": {
                "html": "<br><p id='5' data-category='paragraph' style='font-size:18px'>6, 45</p>",
                "markdown": "6, 45",
                "text": ""
            },
            "coordinates": [
                {
                    "x": 0.461,
                    "y": 0.708
                },
                {
                    "x": 0.5072,
                    "y": 0.708
                },
                {
                    "x": 0.5072,
                    "y": 0.7253
                },
                {
                    "x": 0.461,
                    "y": 0.7253
                }
            ],
            "id": 5,
            "page": 1
        },
        {
            "category": "list",
            "content": {
                "html": "<br><p id='6' data-category='list' style='font-size:18px'>42 Battery-chamber cover latch 43<br>43 Hole to hook Vertical Battery Grip<br>44 Battery-chamber cover. 43<br>45 DISP (display)/ BACK button 22, 216</p>",
                "markdown": "- 42 Battery-chamber cover latch 43\n- 43 Hole to hook Vertical Battery Grip\n- 44 Battery-chamber cover. 43\n- 45 DISP (display)/ BACK button 22, 216\n",
                "text": ""
            },
            "coordinates": [
                {
                    "x": 0.1111,
                    "y": 0.7244
                },
                {
                    "x": 0.5071,
                    "y": 0.7244
                },
                {
                    "x": 0.5071,
                    "y": 0.8089
                },
                {
                    "x": 0.1111,
                    "y": 0.8089
                }
            ],
            "id": 6,
            "page": 1
        },
        {
            "category": "list",
            "content": {
                "html": "<br><p id='7' data-category='list' style='font-size:18px'>46 (playback) button 63<br>47 Speaker 73, 341<br>48 MENU/OK button 32<br>49 AEL (exposure lock) button 111, 385<br>50 Focus stick (focus lever). 6, 98, 357<br>51 Tripod mount<br>52 Vertical battery grip connector cover · 411<br>53 Tilt lock release 11<br>54 LCD monitor 11, 18, 20<br>Touch screen 34, 162, 203<br>55 Headphonejack (⌀3.5mm) 207<br>56 Memory card slot 1<br>(for Type B CFexpress cards) 45<br>57 Memory card slot 2<br>(for SD memory cards) 45</p>",
                "markdown": "- 46 (playback) button 63\n- 47 Speaker 73, 341\n- 48 MENU/OK button 32\n- 49 AEL (exposure lock) button 111, 385\n- 50 Focus stick (focus lever). 6, 98, 357\n- 51 Tripod mount\n- 52 Vertical battery grip connector cover · 411\n- 53 Tilt lock release 11\n- 54 LCD monitor 11, 18, 20\n- Touch screen 34, 162, 203\n- 55 Headphonejack (⌀3.5mm) 207\n- 56 Memory card slot 1\n- (for Type B CFexpress cards) 45\n- 57 Memory card slot 2\n- (for SD memory cards) 45\n",
                "text": ""
            },
            "coordinates": [
                {
                    "x": 0.5345,
                    "y": 0.4847
                },
                {
                    "x": 0.9222,
                    "y": 0.4847
                },
                {
                    "x": 0.9222,
                    "y": 0.7866
                },
                {
                    "x": 0.5345,
                    "y": 0.7866
                }
            ],
            "id": 7,
            "page": 1
        },
        {
            "category": "footer",
            "content": {
                "html": "<footer id='8' style='font-size:20px'>3</footer>",
                "markdown": "3",
                "text": ""
            },
            "coordinates": [
                {
                    "x": 0.8953,
                    "y": 0.9568
                },
                {
                    "x": 0.9167,
                    "y": 0.9568
                },
                {
                    "x": 0.9167,
                    "y": 0.9794
                },
                {
                    "x": 0.8953,
                    "y": 0.9794
                }
            ],
            "id": 8,
            "page": 1
        },
        {
            "category": "footer",
            "content": {
                "html": "<br><footer id='9' style='font-size:22px'>Before<br>You<br>Begin</footer>",
                "markdown": "Before\nYou\nBegin",
                "text": ""
            },
            "coordinates": [
                {
                    "x": 0.9562,
                    "y": 0.278
                },
                {
                    "x": 0.9817,
                    "y": 0.278
                },
                {
                    "x": 0.9817,
                    "y": 0.4018
                },
                {
                    "x": 0.9562,
                    "y": 0.4018
                }
            ],
            "id": 9,
            "page": 1
        }
    ],
    "model": "document-parse-240910",
    "usage": {
        "pages": 1
    }
}