{
    "parsing_result": "\n## Lenses Without Aperture Rings\n\nUsers of lenses with no aperture ring can rotate the command dial past minimum aperture to select **A** (auto), then press the center of the dial to cycle to **S.S. (PROGRAM SHIFT)** and use program shift to choose other combinations of shutter speed and aperture that will produce the same exposure.\n\n## Previewing Depth of Field\n\nWhen **PREVIEW DEPTH OF FIELD** is assigned to a function button, pressing the button displays a !Preview Depth of Field Icon icon and stops aperture down to the selected setting, allowing depth of field to be previewed in the display (📖 253).\n\n!Depth of Field Display\n",
    "embedding_result": [],
    "metadata": {
        "page": 64,
        "model": "x-e4"
    }
}