{
    "pages": [
        {
            "page": 1,
            "md": "# AC-5VJ AC Power Adapter Specifications\n\n| Specification                | Details                                                                                     |\n|------------------------------|---------------------------------------------------------------------------------------------|\n| **Manufacturer**             | Dongguan Yingjiu Power Co., Ltd.                                                            |\n| **Address**                  | No.6 Yongxing Road, Shayao Village, Shijie Town, 523292 Dongguan City, Guangdong Province, PEOPLE'S REPUBLIC OF CHINA |\n| **Model name**               | AC-5VJ                                                                                      |\n| **Rated input**              | 100 V – 240 V AC, 50/60 Hz                                                                  |\n| **Input capacity**           | Max. 50 VA                                                                                  |\n| **Rated output**             | DC5.0V 3.0A 15.0W                                                                           |\n| **Average active efficiency**| 84.8 %                                                                                      |\n| **Efficiency at load 10%**   | 84.2 %                                                                                      |\n| **No-load power consumption**| 0.02 W                                                                                      |\n| **Operating temperature**    | 0 °C to +40 °C/+32 °F to +104 °F                                                            |\n| **Weight**                   | Approx. 45 g ± 2 g/1.6 oz. ± 0.1 oz.                                                        |\n\n> ⚠️ **Note:**  \n> Specifications and performance are subject to change without notice. Fujifilm will not be held liable for any errors this manual may contain. The appearance of the product may differ from that described in this manual.",
            "images": [
                {
                    "name": "page_1.jpg",
                    "height": 0,
                    "width": 0,
                    "x": 0,
                    "y": 0,
                    "type": "full_page_screenshot"
                }
            ],
            "charts": [],
            "items": [
                {
                    "type": "heading",
                    "lvl": 1,
                    "value": "AC-5VJ AC Power Adapter Specifications",
                    "md": "# AC-5VJ AC Power Adapter Specifications"
                },
                {
                    "type": "table",
                    "rows": [
                        [
                            "Specification",
                            "Details"
                        ],
                        [
                            "**Manufacturer**",
                            "Dongguan Yingjiu Power Co., Ltd."
                        ],
                        [
                            "**Address**",
                            "No.6 Yongxing Road, Shayao Village, Shijie Town, 523292 Dongguan City, Guangdong Province, PEOPLE'S REPUBLIC OF CHINA"
                        ],
                        [
                            "**Model name**",
                            "AC-5VJ"
                        ],
                        [
                            "**Rated input**",
                            "100 V – 240 V AC, 50/60 Hz"
                        ],
                        [
                            "**Input capacity**",
                            "Max. 50 VA"
                        ],
                        [
                            "**Rated output**",
                            "DC5.0V 3.0A 15.0W"
                        ],
                        [
                            "**Average active efficiency**",
                            "84.8 %"
                        ],
                        [
                            "**Efficiency at load 10%**",
                            "84.2 %"
                        ],
                        [
                            "**No-load power consumption**",
                            "0.02 W"
                        ],
                        [
                            "**Operating temperature**",
                            "0 °C to +40 °C/+32 °F to +104 °F"
                        ],
                        [
                            "**Weight**",
                            "Approx. 45 g ± 2 g/1.6 oz. ± 0.1 oz."
                        ]
                    ],
                    "md": "| Specification                | Details                                                                                     |\n|------------------------------|---------------------------------------------------------------------------------------------|\n| **Manufacturer**             | Dongguan Yingjiu Power Co., Ltd.                                                            |\n| **Address**                  | No.6 Yongxing Road, Shayao Village, Shijie Town, 523292 Dongguan City, Guangdong Province, PEOPLE'S REPUBLIC OF CHINA |\n| **Model name**               | AC-5VJ                                                                                      |\n| **Rated input**              | 100 V – 240 V AC, 50/60 Hz                                                                  |\n| **Input capacity**           | Max. 50 VA                                                                                  |\n| **Rated output**             | DC5.0V 3.0A 15.0W                                                                           |\n| **Average active efficiency**| 84.8 %                                                                                      |\n| **Efficiency at load 10%**   | 84.2 %                                                                                      |\n| **No-load power consumption**| 0.02 W                                                                                      |\n| **Operating temperature**    | 0 °C to +40 °C/+32 °F to +104 °F                                                            |\n| **Weight**                   | Approx. 45 g ± 2 g/1.6 oz. ± 0.1 oz.                                                        |",
                    "isPerfectTable": true,
                    "csv": "\"Specification\",\"Details\"\n\"**Manufacturer**\",\"Dongguan Yingjiu Power Co., Ltd.\"\n\"**Address**\",\"No.6 Yongxing Road, Shayao Village, Shijie Town, 523292 Dongguan City, Guangdong Province, PEOPLE'S REPUBLIC OF CHINA\"\n\"**Model name**\",\"AC-5VJ\"\n\"**Rated input**\",\"100 V – 240 V AC, 50/60 Hz\"\n\"**Input capacity**\",\"Max. 50 VA\"\n\"**Rated output**\",\"DC5.0V 3.0A 15.0W\"\n\"**Average active efficiency**\",\"84.8 %\"\n\"**Efficiency at load 10%**\",\"84.2 %\"\n\"**No-load power consumption**\",\"0.02 W\"\n\"**Operating temperature**\",\"0 °C to +40 °C/+32 °F to +104 °F\"\n\"**Weight**\",\"Approx. 45 g ± 2 g/1.6 oz. ± 0.1 oz.\""
                },
                {
                    "type": "text",
                    "value": "> ⚠️ **Note:**  \n> Specifications and performance are subject to change without notice. Fujifilm will not be held liable for any errors this manual may contain. The appearance of the product may differ from that described in this manual.",
                    "md": "> ⚠️ **Note:**  \n> Specifications and performance are subject to change without notice. Fujifilm will not be held liable for any errors this manual may contain. The appearance of the product may differ from that described in this manual."
                }
            ],
            "status": "OK",
            "links": [],
            "triggeredAutoMode": false,
            "structuredData": null,
            "noStructuredContent": false,
            "noTextContent": false
        }
    ],
    "job_metadata": {
        "credits_used": 11.0,
        "job_credits_usage": 10,
        "job_pages": 1,
        "job_auto_mode_triggered_pages": 0,
        "job_is_cache_hit": false,
        "credits_max": 1000
    },
    "job_id": "d98053b3-d675-4f96-9b08-bf3ce9260fc9",
    "file_path": "../data/raw_data/gfx100ii/gfx100ii_split/gfx100ii_page497.pdf"
}