{
    "api": "2.0",
    "content": {
        "html": "<header id='0' style='font-size:16px'>Recording Movies</header>\n<h1 id='1' style='font-size:20px'>(Movie) Mode</h1>\n<br><p id='2' data-category='paragraph' style='font-size:16px'>For more control over camera settings, rotate the mode dial to<br>(movie) and record movies using the shutter button.</p>\n<h1 id='3' style='font-size:18px'>1 Rotate the mode dial to (movie).</h1>\n<br><figure id='4'><img style='font-size:14px' alt=\"d S\nAUTO\nV\n-11 20 W\n5\nFILI ER\n♡ 0\" data-coord=\"top-left:(1747,739); bottom-right:(2534,1205)\" /></figure>\n<p id='5' data-category='paragraph' style='font-size:18px'>2 Press the shutter button to start recording.</p>\n<p id='6' data-category='paragraph' style='font-size:14px'>4</p>\n<br><p id='7' data-category='list' style='font-size:18px'>A recording indicator is dis- 1h12m36s<br>1h07m24s<br>played while recording is in prog- perion ⌀<br>1h12m36s<br>ress.<br>1h07m24s<br>The borders of the display turn<br>red during movie recording, green<br>during high-speed recording.<br>● The time remaining is shown by a Recording time<br>countdown display, while another<br>Time remaining<br>display counts up to show the re-<br>cording time.</p>\n<p id='8' data-category='list' style='font-size:18px'>3 Press the shutter button again to end recording.<br>Recording ends automatically when the maximum length is<br>reached or the memory card is full.</p>\n<br><footer id='9' style='font-size:22px'>Movie<br>Recording<br>and<br>Playback</footer>\n<footer id='10' style='font-size:20px'>57</footer>",
        "markdown": "Recording Movies\n\n# (Movie) Mode\n\nFor more control over camera settings, rotate the mode dial to\n(movie) and record movies using the shutter button.\n\n# 1 Rotate the mode dial to (movie).\n\n![image](/image/placeholder)\nd S\nAUTO\nV\n-11 20 W\n5\nFILI ER\n♡ 0\n\n2 Press the shutter button to start recording.\n\n4\n\n- A recording indicator is dis- 1h12m36s\n- 1h07m24s\n- played while recording is in prog- perion ⌀\n- 1h12m36s\n- ress.\n- 1h07m24s\n- The borders of the display turn\n- red during movie recording, green\n- during high-speed recording.\n- ● The time remaining is shown by a Recording time\n- countdown display, while another\n- Time remaining\n- display counts up to show the re-\n- cording time.\n\n\n- 3 Press the shutter button again to end recording.\n- Recording ends automatically when the maximum length is\n- reached or the memory card is full.\n\n\nMovie\nRecording\nand\nPlayback\n\n57",
        "text": ""
    },
    "elements": [
        {
            "category": "header",
            "content": {
                "html": "<header id='0' style='font-size:16px'>Recording Movies</header>",
                "markdown": "Recording Movies",
                "text": ""
            },
            "coordinates": [
                {
                    "x": 0.7375,
                    "y": 0.0286
                },
                {
                    "x": 0.918,
                    "y": 0.0286
                },
                {
                    "x": 0.918,
                    "y": 0.0505
                },
                {
                    "x": 0.7375,
                    "y": 0.0505
                }
            ],
            "id": 0,
            "page": 1
        },
        {
            "category": "heading1",
            "content": {
                "html": "<h1 id='1' style='font-size:20px'>(Movie) Mode</h1>",
                "markdown": "# (Movie) Mode",
                "text": ""
            },
            "coordinates": [
                {
                    "x": 0.1198,
                    "y": 0.0733
                },
                {
                    "x": 0.341,
                    "y": 0.0733
                },
                {
                    "x": 0.341,
                    "y": 0.0984
                },
                {
                    "x": 0.1198,
                    "y": 0.0984
                }
            ],
            "id": 1,
            "page": 1
        },
        {
            "category": "paragraph",
            "content": {
                "html": "<br><p id='2' data-category='paragraph' style='font-size:16px'>For more control over camera settings, rotate the mode dial to<br>(movie) and record movies using the shutter button.</p>",
                "markdown": "For more control over camera settings, rotate the mode dial to\n(movie) and record movies using the shutter button.",
                "text": ""
            },
            "coordinates": [
                {
                    "x": 0.1094,
                    "y": 0.105
                },
                {
                    "x": 0.9176,
                    "y": 0.105
                },
                {
                    "x": 0.9176,
                    "y": 0.1554
                },
                {
                    "x": 0.1094,
                    "y": 0.1554
                }
            ],
            "id": 2,
            "page": 1
        },
        {
            "category": "heading1",
            "content": {
                "html": "<h1 id='3' style='font-size:18px'>1 Rotate the mode dial to (movie).</h1>",
                "markdown": "# 1 Rotate the mode dial to (movie).",
                "text": ""
            },
            "coordinates": [
                {
                    "x": 0.1223,
                    "y": 0.1776
                },
                {
                    "x": 0.6093,
                    "y": 0.1776
                },
                {
                    "x": 0.6093,
                    "y": 0.2018
                },
                {
                    "x": 0.1223,
                    "y": 0.2018
                }
            ],
            "id": 3,
            "page": 1
        },
        {
            "category": "figure",
            "content": {
                "html": "<br><figure id='4'><img style='font-size:14px' alt=\"d S\nAUTO\nV\n-11 20 W\n5\nFILI ER\n♡ 0\" data-coord=\"top-left:(1747,739); bottom-right:(2534,1205)\" /></figure>",
                "markdown": "![image](/image/placeholder)\nd S\nAUTO\nV\n-11 20 W\n5\nFILI ER\n♡ 0",
                "text": ""
            },
            "coordinates": [
                {
                    "x": 0.6322,
                    "y": 0.1898
                },
                {
                    "x": 0.9168,
                    "y": 0.1898
                },
                {
                    "x": 0.9168,
                    "y": 0.3091
                },
                {
                    "x": 0.6322,
                    "y": 0.3091
                }
            ],
            "id": 4,
            "page": 1
        },
        {
            "category": "paragraph",
            "content": {
                "html": "<p id='5' data-category='paragraph' style='font-size:18px'>2 Press the shutter button to start recording.</p>",
                "markdown": "2 Press the shutter button to start recording.",
                "text": ""
            },
            "coordinates": [
                {
                    "x": 0.1244,
                    "y": 0.3351
                },
                {
                    "x": 0.6941,
                    "y": 0.3351
                },
                {
                    "x": 0.6941,
                    "y": 0.36
                },
                {
                    "x": 0.1244,
                    "y": 0.36
                }
            ],
            "id": 5,
            "page": 1
        },
        {
            "category": "paragraph",
            "content": {
                "html": "<p id='6' data-category='paragraph' style='font-size:14px'>4</p>",
                "markdown": "4",
                "text": ""
            },
            "coordinates": [
                {
                    "x": 0.9587,
                    "y": 0.4194
                },
                {
                    "x": 0.9739,
                    "y": 0.4194
                },
                {
                    "x": 0.9739,
                    "y": 0.4361
                },
                {
                    "x": 0.9587,
                    "y": 0.4361
                }
            ],
            "id": 6,
            "page": 1
        },
        {
            "category": "list",
            "content": {
                "html": "<br><p id='7' data-category='list' style='font-size:18px'>A recording indicator is dis- 1h12m36s<br>1h07m24s<br>played while recording is in prog- perion ⌀<br>1h12m36s<br>ress.<br>1h07m24s<br>The borders of the display turn<br>red during movie recording, green<br>during high-speed recording.<br>● The time remaining is shown by a Recording time<br>countdown display, while another<br>Time remaining<br>display counts up to show the re-<br>cording time.</p>",
                "markdown": "- A recording indicator is dis- 1h12m36s\n- 1h07m24s\n- played while recording is in prog- perion ⌀\n- 1h12m36s\n- ress.\n- 1h07m24s\n- The borders of the display turn\n- red during movie recording, green\n- during high-speed recording.\n- ● The time remaining is shown by a Recording time\n- countdown display, while another\n- Time remaining\n- display counts up to show the re-\n- cording time.\n",
                "text": ""
            },
            "coordinates": [
                {
                    "x": 0.1473,
                    "y": 0.365
                },
                {
                    "x": 0.9127,
                    "y": 0.365
                },
                {
                    "x": 0.9127,
                    "y": 0.6223
                },
                {
                    "x": 0.1473,
                    "y": 0.6223
                }
            ],
            "id": 7,
            "page": 1
        },
        {
            "category": "list",
            "content": {
                "html": "<p id='8' data-category='list' style='font-size:18px'>3 Press the shutter button again to end recording.<br>Recording ends automatically when the maximum length is<br>reached or the memory card is full.</p>",
                "markdown": "- 3 Press the shutter button again to end recording.\n- Recording ends automatically when the maximum length is\n- reached or the memory card is full.\n",
                "text": ""
            },
            "coordinates": [
                {
                    "x": 0.1224,
                    "y": 0.6411
                },
                {
                    "x": 0.9204,
                    "y": 0.6411
                },
                {
                    "x": 0.9204,
                    "y": 0.7183
                },
                {
                    "x": 0.1224,
                    "y": 0.7183
                }
            ],
            "id": 8,
            "page": 1
        },
        {
            "category": "footer",
            "content": {
                "html": "<br><footer id='9' style='font-size:22px'>Movie<br>Recording<br>and<br>Playback</footer>",
                "markdown": "Movie\nRecording\nand\nPlayback",
                "text": ""
            },
            "coordinates": [
                {
                    "x": 0.9562,
                    "y": 0.4359
                },
                {
                    "x": 0.9834,
                    "y": 0.4359
                },
                {
                    "x": 0.9834,
                    "y": 0.6804
                },
                {
                    "x": 0.9562,
                    "y": 0.6804
                }
            ],
            "id": 9,
            "page": 1
        },
        {
            "category": "footer",
            "content": {
                "html": "<footer id='10' style='font-size:20px'>57</footer>",
                "markdown": "57",
                "text": ""
            },
            "coordinates": [
                {
                    "x": 0.878,
                    "y": 0.9565
                },
                {
                    "x": 0.9164,
                    "y": 0.9565
                },
                {
                    "x": 0.9164,
                    "y": 0.979
                },
                {
                    "x": 0.878,
                    "y": 0.979
                }
            ],
            "id": 10,
            "page": 1
        }
    ],
    "model": "document-parse-240910",
    "usage": {
        "pages": 1
    }
}