{
    "parsing_result": "\n# IMAGE QUALITY SETTING (Still Photography)\n\n## MOUNT ADAPTER SETTING\n\nAdjust settings for lenses attached via a mount adapter. The camera can store settings for multiple lenses (**LENS 1** through **LENS 6**).\n\n> 💡 **Note:**  \n> Any changes made using this item also apply in movie mode.\n\n### Choosing a Focal Length\n\nEnter the lens’s true focal length.\n\n!Input Focal Length\n\n### Distortion Correction\n\nChoose from **STRONG**, **MEDIUM**, or **WEAK** options to correct **BARREL** or **PINCUSHION** distortion.\n\n!Lens Distortion Correction\n\n### Color Shading Correction\n\nColor (shading) variations between the center and edges of the frame can be adjusted separately for each corner. To use color shading correction, follow the steps below.\n\n1. Rotate the front command dial to choose a corner. The selected corner is indicated by a triangle.\n\n!Color Shading Correction\n",
    "embedding_result": [],
    "metadata": {
        "page": 123,
        "model": "x-e4",
        "subsection": [
            "MOUNT ADAPTER SETTING"
        ],
        "chapter": "The Shooting Menus",
        "section": "IMAGE QUALITY SETTING (Still Photography)"
    }
}