{
    "parsing_result": "# Menu List\n\n## AF/MF Setting\n- **Focus Area** - 146\n- **AF Mode** - 146\n- **Zone Custom Setting** - 146\n- **AF Mode All Setting** - 146\n- **AF-C Custom Settings** - 147\n- **Store AF Mode by Orientation** - 150\n- **AF Point Display** - 151\n- **Wrap Focus Point** - 151\n- **Number of Focus Points** - 151\n- **Pre-AF** - 152\n- **AF Illuminator** - 152\n- **Face/Eye Detection Setting** - 153\n- **Subject Detection Setting** - 155\n- **AF+MF** - 157\n- **MF Assist** - 158\n- **Interlock MF Assist & Focus Ring** - 158\n- **Focus Check** - 159\n- **Interlock Spot AE & Focus Area** - 159\n- **Instant AF Setting** - 159\n- **Depth-of-Field Scale** - 160\n- **Release/Focus Priority** - 160\n- **AF Range Limiter** - 161\n- **Touch Screen Mode** - 162\n\n## Shooting Setting\n- **Self-Timer** - 164\n- **Save Self-Timer Setting** - 165\n- **Self-Timer Lamp** - 165\n- **Interval Timer Shooting** - 166\n- **Interval Timer Shooting Exposure Smoothing** - 168\n- **Interval Priority Mode** - 168\n- **AE BKT Setting** - 169\n- **Film Simulation BKT** - 169\n- **Focus BKT Setting** - 169\n- **Photometry** - 169\n- **Shutter Type** - 170\n- **Flicker Reduction** - 171\n- **Flickerless S.S. Setting** - 171\n- **ISO** - 171\n- **IS Mode** - 172\n- **35mm Format Mode** - 172\n- **Cooling Fan Setting** - 173\n- **Wireless Communication** - 173\n\n## Flash Setting\n- **Flash Function Setting** - 174\n- **Red Eye Removal** - 174\n- **TTL-Lock Mode** - 175\n- **LED Light Setting** - 175\n- **Commander Setting** - 176\n- **CH Setting** - 176",
    "embedding_result": [],
    "metadata": {
        "page": 5,
        "model": "gfx100ii"
    }
}